{
   "abstract" : "Parse record-oriented data in a text file",
   "author" : [
      "Ken Youens-Clark <kclark@cpan.org>"
   ],
   "dynamic_config" : 0,
   "generated_by" : "Module::Build version 0.4003, CPAN::Meta::Converter version 2.112150",
   "license" : [
      "open_source"
   ],
   "meta-spec" : {
      "url" : "http://search.cpan.org/perldoc?CPAN::Meta::Spec",
      "version" : "2"
   },
   "name" : "Text-RecordParser",
   "prereqs" : {
      "build" : {
         "requires" : {
            "Test::Exception" : 0,
            "Test::More" : 0
         }
      },
      "runtime" : {
         "recommends" : {
            "GraphViz" : 0,
            "Readonly::XS" : 0,
            "Text::TabularDisplay" : "1.22"
         },
         "requires" : {
            "Class::Accessor" : 0,
            "IO::Scalar" : 0,
            "List::MoreUtils" : 0,
            "List::Util" : 0,
            "Readonly" : 0,
            "version" : 0
         }
      }
   },
   "provides" : {
      "Text::RecordParser" : {
         "file" : "lib/Text/RecordParser.pm",
         "version" : "v1.6.0"
      },
      "Text::RecordParser::Object" : {
         "file" : "lib/Text/RecordParser/Object.pm",
         "version" : "v1.4.0"
      },
      "Text::RecordParser::Tab" : {
         "file" : "lib/Text/RecordParser/Tab.pm",
         "version" : "v1.4.0"
      }
   },
   "release_status" : "stable",
   "resources" : {
      "license" : [
         "http://opensource.org/licenses/gpl-license.php"
      ]
   },
   "version" : "v1.6.0"
}
